protools/__init__.py
protools/_version.py
protools/aa.py
protools/dock.py
protools/pdbanno.py
protools/pdbconvert.py
protools/pdbextract.py
protools/pdbfixer.py
protools/pdbio.py
protools/pdbplot.py
protools/seqanno.py
protools/seqconvert.py
protools/seqfilter.py
protools/seqfixer.py
protools/seqio.py
protools/seqplot.py
protools/typedef.py
protools/utils.py
protools/cluster/__init__.py
protools/cluster/cdhit.py
protools/cluster/mmseqs.py
protools/database/__init__.py
protools/database/patent.py
protools/database/uniprot.py
protools/dataset/__init__.py
protools/dataset/split.py
protools4py-1.3.4.dist-info/licenses/LICENSE
protools4py-1.3.4.dist-info/METADATA
protools4py-1.3.4.dist-info/WHEEL
protools4py-1.3.4.dist-info/top_level.txt
protools4py-1.3.4.dist-info/RECORD
