Metadata-Version: 2.4
Name: protools4py
Version: 1.3.4
Summary: A simple python package for protein process
Author-email: "Zhang.H.N" <zhang.h.n@foxmail.com>
License: MIT
Project-URL: Homepage, https://github.com/GCS-ZHN/protools
Project-URL: Bug Tracker, https://github.com/GCS-ZHN/protools/issues
Classifier: Programming Language :: Python :: 3
Classifier: License :: OSI Approved :: MIT License
Classifier: Operating System :: OS Independent
Classifier: Topic :: Scientific/Engineering :: Bio-Informatics
Requires-Python: >=3.10
License-File: LICENSE
Requires-Dist: biopython>=1.82
Requires-Dist: pandas
Requires-Dist: tqdm
Requires-Dist: scipy
Requires-Dist: dnachisel
Requires-Dist: antpack<0.3.9,>=0.3.8
Requires-Dist: requests
Requires-Dist: seaborn
Requires-Dist: dockq>=2.1.3
Requires-Dist: pdbfixer
Requires-Dist: prody>=2.6.1
Dynamic: license-file
